avrng/__init__.py
avrng/avrng.py
avrng-1.0.dist-info/LICENSE
avrng-1.0.dist-info/METADATA
avrng-1.0.dist-info/WHEEL
avrng-1.0.dist-info/top_level.txt
avrng-1.0.dist-info/RECORD
