Metadata-Version: 2.1
Name: avrng
Version: 1.0
Summary: An AVRNG implementation
Home-page: https://github.com/kewbish/avrng
Author: Emilie Ma
Author-email: kewbish@gmail.com
License: UNKNOWN
Platform: UNKNOWN
Classifier: Programming Language :: Python :: 3
Classifier: License :: OSI Approved :: GNU General Public License v3 (GPLv3)
Classifier: Operating System :: OS Independent
Requires-Python: >=3.5
Requires-Dist: pydub (==0.23.1)
Requires-Dist: pyskein (==1.0)
Requires-Dist: scenedetect (==0.5.1.1)
Requires-Dist: opencv-python (==4.1.2.30)
